aptx_activation/__init__.py
aptx_activation-0.0.5.dist-info/METADATA
aptx_activation-0.0.5.dist-info/WHEEL
aptx_activation-0.0.5.dist-info/top_level.txt
aptx_activation-0.0.5.dist-info/RECORD
